{
  "generated_at": "2026-06-12T04:30:57",
  "snapshot_id": "89f0dcec1638050c",
  "name": "AutoPaperReader Wiki",
  "count": 5,
  "publish_ready": false,
  "publish_checks": {
    "metadata_complete": true,
    "taxonomy_clean": true,
    "no_duplicate_reports": true,
    "has_review_plan": false,
    "has_generated_pages": true,
    "artifacts_present": true
  },
  "quality_score": 92.0,
  "coverage": {
    "taxonomy": "100%",
    "review_plan": "0%",
    "code_observation": "100%",
    "research_lines": 2
  },
  "queue_sizes": {
    "quality": {
      "missing_required_metadata": 0,
      "needs_review_plan": 5,
      "due_review": 0,
      "no_code_observation": 0,
      "taxonomy_drift": 0,
      "duplicate_reports": 0,
      "taxonomy_sparse": 0,
      "taxonomy_dense": 2,
      "high_importance": 2
    },
    "review": {
      "due": 0,
      "needs_plan": 5,
      "scheduled": 0,
      "high_priority": 2
    },
    "inbox": {
      "count": 0,
      "duplicates": 0
    }
  },
  "risk_queue_sizes": {
    "missing_required_metadata": 0,
    "taxonomy_drift": 0,
    "duplicate_reports": 0,
    "needs_review_plan": 5,
    "due_review": 0,
    "freshness_due": 0,
    "freshness_stale": 0,
    "inbox_duplicates": 0
  },
  "action_groups": [
    {
      "group": "taxonomy",
      "count": 57
    },
    {
      "group": "review",
      "count": 5
    }
  ],
  "governance_policy": {
    "taxonomy_load": {
      "min_structure_labels": 3,
      "min_tags": 3,
      "max_tags": 10,
      "max_methods": 8
    },
    "taxonomy_actions": {
      "singleton_max_count": 1,
      "watch_share": 0.4,
      "watch_min_count": 4,
      "split_share": 0.6,
      "split_min_count": 5
    },
    "taxonomy_balance": {
      "high_score_below": 45,
      "medium_score_below": 70,
      "singleton_medium_count": 3,
      "unused_medium_count": 3
    },
    "coverage": {
      "high_score_below": 70,
      "medium_score_below": 90,
      "missing_high_min": 2
    }
  },
  "active_status_workflow": "personal",
  "research_lines": [
    {
      "name": "Parallel Decoding with Diffusion Models",
      "count": 3,
      "owner": "decoding-owner",
      "team": "generation",
      "cadence": "biweekly",
      "owner_note": "Track diffusion language model and speculative decoding updates.",
      "roles": {
        "followup": 1,
        "foundation": 1,
        "variant": 1
      },
      "code_coverage": "100%",
      "avg_importance": 4.3
    },
    {
      "name": "Efficient Attention Kernels",
      "count": 2,
      "owner": "kernel-owner",
      "team": "systems",
      "cadence": "monthly",
      "owner_note": "Review new GPU kernel and serving papers.",
      "roles": {
        "foundation": 1,
        "system": 1
      },
      "code_coverage": "100%",
      "avg_importance": 4.5
    }
  ],
  "artifact_summary": {
    "count": 52,
    "missing": [],
    "hashes": [
      {
        "href": "index.html",
        "kind": "page",
        "sha256": "9341448bf9f574e38f7f4649b5bfef6b1a33ce407c70dd5971821e923306b1b2",
        "status": "ok"
      },
      {
        "href": "library.html",
        "kind": "page",
        "sha256": "3877ee8cb6b22425761751dd186046f4f1d3d271b0d197b3e29164df53067817",
        "status": "ok"
      },
      {
        "href": "dashboard.html",
        "kind": "page",
        "sha256": "68c8d7b7e2c82c790ae486defbcee3fd9f173d5aa80fbe1b7e7d4d507cb8da21",
        "status": "ok"
      },
      {
        "href": "actions.html",
        "kind": "page",
        "sha256": "0948c0091b4791398186b09353f90d31323215cc2826cb31a884a8f2ff17fbf6",
        "status": "ok"
      },
      {
        "href": "collections.html",
        "kind": "page",
        "sha256": "3659babbb6fd6fd11d19c0040bc84fb8929f3361a250da0498bf6bafa9aa7c7d",
        "status": "ok"
      },
      {
        "href": "balance.html",
        "kind": "page",
        "sha256": "e1007fc35900dcf58635ed8566fe0c2d3b58d40ff575258deb0767796ecd08b2",
        "status": "ok"
      },
      {
        "href": "coverage.html",
        "kind": "page",
        "sha256": "0224dc6863bdeee7a5a7e01ffdb5a905ea01e38bf884e54744e002d341d09f80",
        "status": "ok"
      },
      {
        "href": "facets.html",
        "kind": "page",
        "sha256": "f96468fa29d9fd0765bb15972895a0b5672f7163ee81c5836b487d9431f96824",
        "status": "ok"
      },
      {
        "href": "related.html",
        "kind": "page",
        "sha256": "5aaf606798e6263edf82da7f4f992ea203b83cecc3ec6c7d24a97b63070d1e00",
        "status": "ok"
      },
      {
        "href": "gaps.html",
        "kind": "page",
        "sha256": "077ede02ef7309f93f42db6faefb30f0ca827db850502b6bc4467b6a59725ad6",
        "status": "ok"
      },
      {
        "href": "board.html",
        "kind": "page",
        "sha256": "cfa9dd6d8b20182f8e9eac19baf53e21d9a472b9a3ed2fbc44c9da3d6ebcee90",
        "status": "ok"
      },
      {
        "href": "workflow.html",
        "kind": "page",
        "sha256": "1915344df8128204b62050309ce10b929702e53fcc57451ef756a47fbb091f7a",
        "status": "ok"
      },
      {
        "href": "pivot.html",
        "kind": "page",
        "sha256": "d2b6486eed1e528bb3fe12c05429ffd71853ca9322b30ed48a2dc4d65f8ff947",
        "status": "ok"
      },
      {
        "href": "compare.html",
        "kind": "page",
        "sha256": "0f56a97dec85c80d54f1d24734e004e85574055519368c26a9b0b4fb028ce4c3",
        "status": "ok"
      },
      {
        "href": "taxonomy_map.html",
        "kind": "page",
        "sha256": "625c68f8e387d226f0a4ef887fc35df2462792a8548242766ea63a49595db4ea",
        "status": "ok"
      },
      {
        "href": "scale.html",
        "kind": "page",
        "sha256": "2a3946d8709f9d7cf8d41978e1a017366bdce0a37f9c1ee3517599edcfe6b3e7",
        "status": "ok"
      },
      {
        "href": "ownership.html",
        "kind": "page",
        "sha256": "9f7ca050f2c3401c72dcf164c847423ae7b6dc2567c3fdbe008c4d6ca451e0ea",
        "status": "ok"
      },
      {
        "href": "routing.html",
        "kind": "page",
        "sha256": "55542b104d75fec2517b5bf8d434254ab017a56155f07804eec4021d9010f7a6",
        "status": "ok"
      },
      {
        "href": "onboarding.html",
        "kind": "page",
        "sha256": "d79025a5f5671366f578f407d8892704a4fa50b081e9ce0d6d7b294f483655cc",
        "status": "ok"
      },
      {
        "href": "catalog.html",
        "kind": "page",
        "sha256": "fcceb7f7d447c1b79799cbe182352986d21033987ac97be50d710fda5a53f0cc",
        "status": "ok"
      },
      {
        "href": "inbox.html",
        "kind": "page",
        "sha256": "a460cc831a0022a8dea9581c7f657e205c34b291d916b763df51a59bbc33bd79",
        "status": "ok"
      },
      {
        "href": "review.html",
        "kind": "page",
        "sha256": "09746ea2d9cfafc818132d43d68f4c03eeac8343d375181ebaa798235d73ec7e",
        "status": "ok"
      },
      {
        "href": "freshness.html",
        "kind": "page",
        "sha256": "0ff3ca6402f74af25a1d389a851540a642f42c216ecc2009c9a19fb4d0cd70d8",
        "status": "ok"
      },
      {
        "href": "quality.html",
        "kind": "page",
        "sha256": "d7e7439a87b93b383f5ea4dd1a5d0b5194478a8a518797edd9966f8e6e5dcef5",
        "status": "ok"
      },
      {
        "href": "taxonomy.html",
        "kind": "page",
        "sha256": "e28147ec10297424e3845797163cd34985aa16c7ae4d62c381fb5747585f8800",
        "status": "ok"
      },
      {
        "href": "timeline.html",
        "kind": "page",
        "sha256": "be4e37462487a64aa65ed23a9144dbcbef86552627d858ae0b419c0b5e92a4c5",
        "status": "ok"
      },
      {
        "href": "matrix.html",
        "kind": "page",
        "sha256": "c9ce3265d6a4a0971c9bc82946cc1b844c9361714f69691400cce70e9b0f9c94",
        "status": "ok"
      },
      {
        "href": "lines/index.html",
        "kind": "page",
        "sha256": "ccf9be33a06ab7e28017e601a24bc4a11263fababe2f6f9ea6ba837844c5e56a",
        "status": "ok"
      },
      {
        "href": "tags.html",
        "kind": "page",
        "sha256": "057f6ec3b0c15c08b8c5d2519d094b1bc913d7b09d6f49382420ad256354264c",
        "status": "ok"
      },
      {
        "href": "papers.json",
        "kind": "data",
        "sha256": "b103a8fd9a0e8c342245b5f0822427c72976b51bc14157cdd933ff8a36993c3f",
        "status": "ok"
      },
      {
        "href": "search_index.json",
        "kind": "data",
        "sha256": "579be3e758459426baee7f1b525eba92ace91310fe5b69cce13cd0064b9f532e",
        "status": "ok"
      },
      {
        "href": "stats.json",
        "kind": "data",
        "sha256": "24d5f54e128a173795b2e85b16093fcd1eb0401e09ab8e4311c3e3a55a34b29a",
        "status": "ok"
      },
      {
        "href": "quality.json",
        "kind": "data",
        "sha256": "1b9ef209a98861649d825759648da40a4bb39f6281665910d42017e76d58d872",
        "status": "ok"
      },
      {
        "href": "review.json",
        "kind": "data",
        "sha256": "628556f7388d1db6d9fd3119773ef05848b27744dcd1545e58cd7e1e1a335bb4",
        "status": "ok"
      },
      {
        "href": "freshness.json",
        "kind": "data",
        "sha256": "c74e41eb53a9234cc2289c59abe5ee4f716dd1c7ea1ff6715cedebdb78913969",
        "status": "ok"
      },
      {
        "href": "taxonomy_actions.json",
        "kind": "data",
        "sha256": "c5f49a851a57224d02190e09a5379d31c58c7b90f6e2d71d063daea87bba05a7",
        "status": "ok"
      },
      {
        "href": "actions.json",
        "kind": "data",
        "sha256": "95b99f4ef6b2b50da38a5d03afdc519d380cd484ac522be1b3fe0cfc355d50a4",
        "status": "ok"
      },
      {
        "href": "workflow.json",
        "kind": "data",
        "sha256": "fb97c88a6539fa0865c1b284104461f000ccce252effda45b38040a7058e2c8d",
        "status": "ok"
      },
      {
        "href": "pivot.json",
        "kind": "data",
        "sha256": "0e2de211e6e68b71e3ce9b34e6ae3127145dcefd5946cb276b644e5f6d7033e1",
        "status": "ok"
      },
      {
        "href": "compare.json",
        "kind": "data",
        "sha256": "7a56be3782d6736b0509fbfe6035132c770a87ebe423d8a33bd5dbe700fe73b2",
        "status": "ok"
      },
      {
        "href": "taxonomy_map.json",
        "kind": "data",
        "sha256": "c51ca346eafda5741e66a05940c8518c9f4d40f209299e5269902e5c1711cd26",
        "status": "ok"
      },
      {
        "href": "scale.json",
        "kind": "data",
        "sha256": "d0c382d4508eebaab373b685c9abcd99a4046da59ee848d708191ee65674a98a",
        "status": "ok"
      },
      {
        "href": "ownership.json",
        "kind": "data",
        "sha256": "085030bcc6f0b24f9f3536453284fd6d76d050fca09ad5edcd7ed2643bbffc37",
        "status": "ok"
      },
      {
        "href": "routing.json",
        "kind": "data",
        "sha256": "dc894eb3d95bde1a1fc64757ab57c6b1ee3c159630864d479969288f876de20d",
        "status": "ok"
      },
      {
        "href": "onboarding.json",
        "kind": "data",
        "sha256": "d59e6c358a945a2ce30f06a5af66ff6cbe38a01285943f311e50453c36cebd3a",
        "status": "ok"
      },
      {
        "href": "catalog.json",
        "kind": "data",
        "sha256": "d970b5662bc72da03d09adc5b00a6104a8d862b7301f64252ceeb2604a11e6ad",
        "status": "ok"
      },
      {
        "href": "inbox.json",
        "kind": "data",
        "sha256": "16088a733262361546376c706fdad3a3676e45a635dcee5fc3d953ee66e1bf50",
        "status": "ok"
      },
      {
        "href": "guides/report.template.md",
        "kind": "contract",
        "sha256": "698233eb11b0d1f212ef9f1dad719735f337031c5a8ba4c4e142370c5deb3254",
        "status": "ok"
      },
      {
        "href": "guides/metadata.schema.json",
        "kind": "contract",
        "sha256": "246d8f345ead3ced56403a313d89bae2042820432274758166e557c39c04716b",
        "status": "ok"
      },
      {
        "href": "guides/inbox.schema.json",
        "kind": "contract",
        "sha256": "074a6f551809f6d2e301e2d4a3769125a8c7159fc2f1d35f0aff8e3bc9f963b7",
        "status": "ok"
      },
      {
        "href": "guides/taxonomy.schema.json",
        "kind": "contract",
        "sha256": "276570bb1323cdaae8164bb5a84ae460ed561a58125d0741aaa5d7c99ff23533",
        "status": "ok"
      },
      {
        "href": "guides/taxonomy.json",
        "kind": "contract",
        "sha256": "602deee0d4843e701fa86c0f599589ff298cb8436ca2d61e435e85076c80a347",
        "status": "ok"
      }
    ]
  },
  "links": {
    "release": "release.html",
    "manifest": "manifest.json",
    "quality": "quality.json",
    "actions": "actions.json",
    "stats": "stats.json"
  }
}